dropmail/__init__.py
dropmail/_version.py
dropmail/dropmail.py
dropmail_client-2.0.0.dist-info/COPYING
dropmail_client-2.0.0.dist-info/COPYING.LESSER
dropmail_client-2.0.0.dist-info/METADATA
dropmail_client-2.0.0.dist-info/WHEEL
dropmail_client-2.0.0.dist-info/top_level.txt
dropmail_client-2.0.0.dist-info/RECORD
